ivsflex_camera.py
ivsflex_camera-0.1.1.dist-info/METADATA
ivsflex_camera-0.1.1.dist-info/WHEEL
ivsflex_camera-0.1.1.dist-info/RECORD
